{
  "primary": {
    "active": {
      "background-color": {
        "value": "orange",
        "type": "color"
      },
      "color": {
        "value": "{color-usecase.button.primary.active}",
        "type": "color"
      }
    },
    "hover": {
      "background-color": {
        "value": "{color-usecase.background.button.primary.hover}",
        "type": "color"
      },
      "color": {
        "value": "{color-usecase.button.primary.hover}",
        "type": "color"
      }
    }
  },
  "secondary": {
    "active": {
      "background-color": {
        "value": "green",
        "type": "color"
      },
      "color": {
        "value": "{color-usecase.button.secondary.active}",
        "type": "color"
      }
    },
    "hover": {
      "background-color": {
        "value": "{color-usecase.background.button.secondary.hover}",
        "type": "color"
      },
      "color": {
        "value": "{color-usecase.button.secondary.hover}",
        "type": "color"
      }
    }
  },
  "ghost": {
    "active": {
      "background-color": {
        "value": "{color-usecase.background.button.secondary.active}",
        "type": "color"
      },
      "color": {
        "value": "{color-usecase.button.secondary.active}",
        "type": "color"
      }
    },
    "hover": {
      "background-color": {
        "value": "{color-usecase.background.button.secondary.hover}",
        "type": "color"
      },
      "color": {
        "value": "{color-usecase.button.secondary.hover}",
        "type": "color"
      }
    }
  }
}